README.txt
setup.py
csv2graphite/__init__.py
csv2graphite/csv2graphite.py
csv2graphite.egg-info/PKG-INFO
csv2graphite.egg-info/SOURCES.txt
csv2graphite.egg-info/dependency_links.txt
csv2graphite.egg-info/entry_points.txt
csv2graphite.egg-info/top_level.txt
csv2graphite.egg-info/zip-safe